netbox_object_storage/__init__.py
netbox_object_storage/constants.py
netbox_object_storage/navigation.py
netbox_object_storage/tables.py
netbox_object_storage/urls.py
netbox_object_storage/api/__init__.py
netbox_object_storage/api/serializers.py
netbox_object_storage/api/urls.py
netbox_object_storage/api/views.py
netbox_object_storage/filtersets/__init__.py
netbox_object_storage/filtersets/bucket.py
netbox_object_storage/filtersets/cluster.py
netbox_object_storage/filtersets/pool.py
netbox_object_storage/forms/__init__.py
netbox_object_storage/forms/assginment.py
netbox_object_storage/forms/bucket.py
netbox_object_storage/forms/cluster.py
netbox_object_storage/forms/pool.py
netbox_object_storage/migrations/0001_initial.py
netbox_object_storage/migrations/0002_remove_pool_contact_remove_s3cluster_contact_and_more.py
netbox_object_storage/migrations/0003_remove_s3cluster_s3device_count_and_more.py
netbox_object_storage/migrations/__init__.py
netbox_object_storage/models/__init__.py
netbox_object_storage/models/bucket.py
netbox_object_storage/models/cluster.py
netbox_object_storage/models/pool.py
netbox_object_storage/templates/cluster_assignment/base.html
netbox_object_storage/templates/cluster_assignment/cluster_add_devices.html
netbox_object_storage/templates/cluster_assignment/cluster_add_virtualmachine.html
netbox_object_storage/templates/cluster_assignment/device.html
netbox_object_storage/templates/cluster_assignment/device_base.html
netbox_object_storage/templates/cluster_assignment/virtualmachine.html
netbox_object_storage/templates/cluster_assignment/virtualmachine_base.html
netbox_object_storage/templates/netbox_object_storage/bucket.html
netbox_object_storage/templates/netbox_object_storage/bucket_edit.html
netbox_object_storage/templates/netbox_object_storage/pool.html
netbox_object_storage/templates/netbox_object_storage/s3cluster.html
netbox_object_storage/templates/netbox_object_storage/generic/bulk_remove.html
netbox_object_storage/views/__init__.py
netbox_object_storage-1.0.1.dist-info/METADATA
netbox_object_storage-1.0.1.dist-info/WHEEL
netbox_object_storage-1.0.1.dist-info/entry_points.txt
netbox_object_storage-1.0.1.dist-info/top_level.txt
netbox_object_storage-1.0.1.dist-info/RECORD
