Metadata-Version: 2.1
Name: netbox-object-storage
Version: 1.0.1
Summary: Netbox Plugin for Manage S3
Home-page: UNKNOWN
Author: UNKNOWN
Author-email: UNKNOWN
License: UNKNOWN
Platform: UNKNOWN
